chronos/__about__.py
chronos/__init__.py
chronos/base.py
chronos/boto_utils.py
chronos/chronos.py
chronos/chronos_bolt.py
chronos/df_utils.py
chronos/utils.py
chronos/chronos2/__init__.py
chronos/chronos2/config.py
chronos/chronos2/dataset.py
chronos/chronos2/layers.py
chronos/chronos2/model.py
chronos/chronos2/pipeline.py
chronos/chronos2/trainer.py
chronos_forecasting-2.2.2.dist-info/METADATA
chronos_forecasting-2.2.2.dist-info/WHEEL
chronos_forecasting-2.2.2.dist-info/licenses/LICENSE
chronos_forecasting-2.2.2.dist-info/licenses/NOTICE
chronos_forecasting-2.2.2.dist-info/RECORD
