Metadata-Version: 2.4
Name: chronos-forecasting
Version: 2.2.2
Summary: Chronos: Pretrained models for time series forecasting
Project-URL: Homepage, https://github.com/amazon-science/chronos-forecasting
Project-URL: Issues, https://github.com/amazon-science/chronos-forecasting/issues
Project-URL: Chronos-Paper, https://arxiv.org/abs/2403.07815
Project-URL: Chronos-2-Paper, https://arxiv.org/abs/2510.15821
Author-email: Abdul Fatir Ansari <ansarnd@amazon.com>, Lorenzo Stella <stellalo@amazon.com>, Caner Turkmen <atturkm@amazon.com>, Oleksandr Shchur <shchuro@amazon.com>, Jaris Küken <kuekenj@amazon.com>, Andreas Auer <auerand@amazon.com>
License: 
License-File: LICENSE
License-File: NOTICE
Classifier: License :: OSI Approved :: Apache Software License
Classifier: Operating System :: OS Independent
Classifier: Programming Language :: Python :: 3
Classifier: Topic :: Scientific/Engineering :: Artificial Intelligence
Requires-Python: >=3.10
Requires-Dist: accelerate<2,>=0.34
Requires-Dist: einops<1,>=0.7.0
Requires-Dist: numpy<3,>=1.21
Requires-Dist: scikit-learn<2,>=1.6.0
Requires-Dist: torch<3,>=2.2
Requires-Dist: transformers<5,>=4.41
Provides-Extra: dev
Requires-Dist: datasets<4,>=3.0; extra == 'dev'
Requires-Dist: fev>=0.6.1; extra == 'dev'
Requires-Dist: gluonts[pro]~=0.16; extra == 'dev'
Requires-Dist: joblib; extra == 'dev'
Requires-Dist: pandas<2.4,>=2.0; extra == 'dev'
Requires-Dist: rich; extra == 'dev'
Requires-Dist: tensorboard; extra == 'dev'
Requires-Dist: typer; extra == 'dev'
Requires-Dist: typer-config; extra == 'dev'
Provides-Extra: extras
Requires-Dist: boto3<2,>=1.10; extra == 'extras'
Requires-Dist: fev>=0.6.1; extra == 'extras'
Requires-Dist: pandas[pyarrow]<2.4,>=2.0; extra == 'extras'
Requires-Dist: peft<0.18,>=0.13.0; extra == 'extras'
Provides-Extra: test
Requires-Dist: boto3<2,>=1.10; extra == 'test'
Requires-Dist: fev>=0.6.1; extra == 'test'
Requires-Dist: pandas[pyarrow]<2.4,>=2.0; extra == 'test'
Requires-Dist: peft<1,>=0.13.0; extra == 'test'
Requires-Dist: pytest~=8.0; extra == 'test'
Provides-Extra: typecheck
Requires-Dist: mypy~=1.9; extra == 'typecheck'
